funkyprompt/__init__.py
funkyprompt/_version.py
funkyprompt/app/__init__.py
funkyprompt/app/api.py
funkyprompt/app/cli.py
funkyprompt/app/main.py
funkyprompt/core/AbstractModel.py
funkyprompt/core/ConversationModel.py
funkyprompt/core/__init__.py
funkyprompt/core/agents/AbstractLanguageModel.py
funkyprompt/core/agents/CallingContext.py
funkyprompt/core/agents/DefaultAgentCore.py
funkyprompt/core/agents/FunctionManager.py
funkyprompt/core/agents/MessageStack.py
funkyprompt/core/agents/Plan.py
funkyprompt/core/agents/QueryClassifier.py
funkyprompt/core/agents/Runner.py
funkyprompt/core/agents/__init__.py
funkyprompt/core/fields/__init__.py
funkyprompt/core/fields/annotations.py
funkyprompt/core/functions/Function.py
funkyprompt/core/functions/__init__.py
funkyprompt/core/types/__init__.py
funkyprompt/core/types/arrow.py
funkyprompt/core/types/avro.py
funkyprompt/core/types/cypher.py
funkyprompt/core/types/inspection.py
funkyprompt/core/types/markdown.py
funkyprompt/core/types/pydantic.py
funkyprompt/core/types/sql.py
funkyprompt/core/utils/__init__.py
funkyprompt/core/utils/dates.py
funkyprompt/core/utils/embeddings.py
funkyprompt/core/utils/env.py
funkyprompt/core/utils/ids.py
funkyprompt/core/utils/openapi.py
funkyprompt/core/utils/parsing/__init__.py
funkyprompt/core/utils/parsing/web.py
funkyprompt/entities/__init__.py
funkyprompt/entities/extra.py
funkyprompt/entities/nodes.py
funkyprompt/entities/relations.py
funkyprompt/services/__init__.py
funkyprompt/services/data/__init__.py
funkyprompt/services/data/duck.py
funkyprompt/services/data/kuzu.py
funkyprompt/services/data/lance.py
funkyprompt/services/data/postgres.py
funkyprompt/services/data/redis.py
funkyprompt/services/data/trifecta.py
funkyprompt/services/data/utils/__init__.py
funkyprompt/services/fs/__init__.py
funkyprompt/services/fs/gfs.py
funkyprompt/services/fs/provider.py
funkyprompt/services/fs/s3.py
funkyprompt/services/models/__init__.py
funkyprompt/services/models/cerebras.py
funkyprompt-0.5.22.dist-info/METADATA
funkyprompt-0.5.22.dist-info/WHEEL
funkyprompt-0.5.22.dist-info/entry_points.txt
funkyprompt-0.5.22.dist-info/RECORD
