Metadata-Version: 2.1
Name: funkyprompt
Version: 0.5.22
Summary: A library for speaking with large langauge models using object orientated generation to build data-rich agentic systems
License: MIT
Author: mr-saoirse
Author-email: amartey@gmail.com
Requires-Python: >=3.10,<4.0
Classifier: License :: OSI Approved :: MIT License
Classifier: Programming Language :: Python :: 3
Classifier: Programming Language :: Python :: 3.10
Classifier: Programming Language :: Python :: 3.11
Requires-Dist: anthropic (>=0.31.2,<0.32.0)
Requires-Dist: beautifulsoup4 (>=4.12.3,<5.0.0)
Requires-Dist: boto3 (>=1.35.24,<2.0.0)
Requires-Dist: datamodel-code-generator (>=0.26.1,<0.27.0)
Requires-Dist: docstring-parser (>=0.16,<0.17)
Requires-Dist: google-generativeai (>=0.7.2,<0.8.0)
Requires-Dist: html2text (>=2024.2.26,<2025.0.0)
Requires-Dist: loguru (>=0.7.2,<0.8.0)
Requires-Dist: markdown (>=3.7,<4.0)
Requires-Dist: openai (>=1.37.1,<2.0.0)
Requires-Dist: psycopg2-binary (>=2.9.9,<3.0.0)
Requires-Dist: pydantic (>=2.8.2,<3.0.0)
Requires-Dist: typer (>=0.12.3,<0.13.0)
